{
  "main": {
    "id": "8bcc5f5cdbe8d1af",
    "type": "split",
    "children": [
      {
        "id": "ee6084fbc462ef98",
        "type": "tabs",
        "children": [
          {
            "id": "171b5569dd9fdadf",
            "type": "leaf",
            "state": {
              "type": "image",
              "state": {
                "file": "SSR_Portfolio/Images/I2C/mpu6050_i2c_message.png"
              },
              "icon": "lucide-image",
              "title": "mpu6050_i2c_message"
            }
          },
          {
            "id": "a1997cbd635acebe",
            "type": "leaf",
            "state": {
              "type": "markdown",
              "state": {
                "file": "SSR_Portfolio/Pages/LoRa/TheThingsNetwork.md",
                "mode": "source",
                "source": false
              },
              "icon": "lucide-file",
              "title": "TheThingsNetwork"
            }
          },
          {
            "id": "6700c1aa35fd9025",
            "type": "leaf",
            "state": {
              "type": "markdown",
              "state": {
                "file": "SSR_Portfolio/Pages/LoRa/Back-End.md",
                "mode": "source",
                "source": false
              },
              "icon": "lucide-file",
              "title": "Back-End"
            }
          }
        ]
      }
    ],
    "direction": "vertical"
  },
  "left": {
    "id": "9c71b15f120aaa88",
    "type": "split",
    "children": [
      {
        "id": "6ba32301cd1e3768",
        "type": "tabs",
        "children": [
          {
            "id": "8a6576b4950a82bc",
            "type": "leaf",
            "state": {
              "type": "file-explorer",
              "state": {
                "sortOrder": "alphabetical"
              },
              "icon": "lucide-folder-closed",
              "title": "Files"
            }
          },
          {
            "id": "695c1d6a4b26f675",
            "type": "leaf",
            "state": {
              "type": "search",
              "state": {
                "query": "",
                "matchingCase": false,
                "explainSearch": false,
                "collapseAll": false,
                "extraContext": false,
                "sortOrder": "alphabetical"
              },
              "icon": "lucide-search",
              "title": "Search"
            }
          },
          {
            "id": "ac892c9b663a0b4d",
            "type": "leaf",
            "state": {
              "type": "bookmarks",
              "state": {},
              "icon": "lucide-bookmark",
              "title": "Bookmarks"
            }
          }
        ]
      }
    ],
    "direction": "horizontal",
    "width": 395.5
  },
  "right": {
    "id": "fa0f3ca27e38a992",
    "type": "split",
    "children": [
      {
        "id": "38932c5f93823f48",
        "type": "tabs",
        "children": [
          {
            "id": "a0c4fbbcc4ba35df",
            "type": "leaf",
            "state": {
              "type": "backlink",
              "state": {
                "file": "SSR_Portfolio/Pages/Server side.md",
                "collapseAll": false,
                "extraContext": false,
                "sortOrder": "alphabetical",
                "showSearch": false,
                "searchQuery": "",
                "backlinkCollapsed": false,
                "unlinkedCollapsed": true
              },
              "icon": "links-coming-in",
              "title": "Backlinks for Server side"
            }
          },
          {
            "id": "5330560d460d681d",
            "type": "leaf",
            "state": {
              "type": "outgoing-link",
              "state": {
                "file": "SSR_Portfolio/Pages/Server side.md",
                "linksCollapsed": false,
                "unlinkedCollapsed": true
              },
              "icon": "links-going-out",
              "title": "Outgoing links from Server side"
            }
          },
          {
            "id": "552e12439208484f",
            "type": "leaf",
            "state": {
              "type": "tag",
              "state": {
                "sortOrder": "frequency",
                "useHierarchy": true
              },
              "icon": "lucide-tags",
              "title": "Tags"
            }
          },
          {
            "id": "45aaa251b9c27733",
            "type": "leaf",
            "state": {
              "type": "outline",
              "state": {
                "file": "SSR_Portfolio/Pages/Server side.md"
              },
              "icon": "lucide-list",
              "title": "Outline of Server side"
            }
          }
        ]
      }
    ],
    "direction": "horizontal",
    "width": 300,
    "collapsed": true
  },
  "left-ribbon": {
    "hiddenItems": {
      "switcher:Open quick switcher": false,
      "graph:Open graph view": false,
      "canvas:Create new canvas": false,
      "daily-notes:Open today's daily note": false,
      "templates:Insert template": false,
      "command-palette:Open command palette": false
    }
  },
  "active": "171b5569dd9fdadf",
  "lastOpenFiles": [
    "PPT/SSR_Mid_PPT.pptx",
    "PPT/Simple.pptx",
    "SSR_Portfolio/Images/Power_Profiling/standby_stm32_current_consumption_close_look.png",
    "SSR_Portfolio/Images/Power_Profiling/standby_stm32_current_consumption.png",
    "SSR_Portfolio/Images/Power_Profiling/sht40_consumption.png",
    "SSR_Portfolio/Images/Power_Profiling/ltr_329_consumption.png",
    "SSR_Portfolio/Images/BLE-program_flow.pdf",
    "SSR_Portfolio/Datasheets/bluefruit-nrf52-feather-learning-guide.pdf",
    "PPT",
    "block diagram.png",
    "SSR_Portfolio/Pages/LoRa/UART communications.md",
    "SSR_Portfolio/Pages/LoRa/TheThingsNetwork.md",
    "SSR_Portfolio/Pages/LoRa/Back-End.md",
    "SSR_Portfolio/Portfolio.md",
    "SSR_Portfolio/Pages/LoRa/Back-End.md",
    "SSR_Portfolio/Images/LoRa/uart_settings.png",
    "SSR_Portfolio/Images/LoRa/uart_test_output.png",
    "SSR_Portfolio/Images/LoRa/Screenshot from 2024-11-19 14-22-56.png",
    "SSR_Portfolio/Images/LoRa/mongodb_connection_creation.png",
    "SSR_Portfolio/Images/LoRa/mongodb_settings.png",
    "ttn_create_application.md",
    "SSR_Portfolio/Fixes Software installations.md",
    "SSR_Portfolio/Images/LoRa/putty_uart_settings.md",
    "SSR_Portfolio/Pages/LoRa/UART.md",
    "Pages/LoRa/UART.md",
    "Pages/LoRa",
    "Pages",
    "SSR_Portfolio/Pages/LoRa/Untitled",
    "SSR_Portfolio/Pages/LoRa",
    "UART.md",
    "SSR_Portfolio/Nice links.md",
    "SSR_Portfolio/Images/LoRa",
    "SSR_Portfolio/Images/brain_flow_diagram.pdf",
    "install docker on linux.md",
    "portfolio.md"
  ]
}